README.md
setup.py
recursion_trace/__init__.py
recursion_trace.egg-info/PKG-INFO
recursion_trace.egg-info/SOURCES.txt
recursion_trace.egg-info/dependency_links.txt
recursion_trace.egg-info/requires.txt
recursion_trace.egg-info/top_level.txt