Metadata-Version: 2.1
Name: recursion-trace
Version: 0.1.3
Summary: A package to trace recursive function calls and generate a recursion tree
Author: Swayam Singh
Author-email: hawkempire007@gmail.com
